magic_print/__init__.py
magic_print/magic_print.py
magic_print-0.1.0.dist-info/METADATA
magic_print-0.1.0.dist-info/WHEEL
magic_print-0.1.0.dist-info/top_level.txt
magic_print-0.1.0.dist-info/RECORD
